lean_qi-0.0.1.dist-info/licenses/LICENSE
leanup/__init__.py
leanup/elan-init.ps1
leanup/elan-init.sh
leanup/main.py
lean_qi-0.0.1.dist-info/METADATA
lean_qi-0.0.1.dist-info/WHEEL
lean_qi-0.0.1.dist-info/entry_points.txt
lean_qi-0.0.1.dist-info/top_level.txt
lean_qi-0.0.1.dist-info/RECORD
