Metadata-Version: 2.4
Name: lean-qi
Version: 0.0.1
Summary: 一个使用镜像源来快速安装 Lean 的简单工具。
Author-email: Hewzhew <hewzhew@bupt.edu.cn>
License: MIT
Keywords: lean,elan,installer,theorem prover
Classifier: Development Status :: 4 - Beta
Classifier: Intended Audience :: Developers
Classifier: License :: OSI Approved :: MIT License
Classifier: Operating System :: OS Independent
Classifier: Programming Language :: Python :: 3
Classifier: Topic :: Software Development :: Build Tools
Requires-Python: >=3.7
License-File: LICENSE
Dynamic: license-file
